expert/VERSION.py
expert/__init__.py
expert/cli.py
expert/document_summarizer.py
expert/kb_builder.py
expert/kb_interface.py
expert/models.py
expert/py.typed
expert_cli-0.1.3.data/scripts/expert
expert_cli-0.1.3.dist-info/METADATA
expert_cli-0.1.3.dist-info/WHEEL
expert_cli-0.1.3.dist-info/top_level.txt
expert_cli-0.1.3.dist-info/RECORD
