Metadata-Version: 2.1
Name: expert-cli
Version: 0.1.3
Summary: 'expert' knowledge assistant
Author: Liam Tengelis
Author-email: liam.tengelis@blacktuskdata.com
Requires-Dist: expert-kb
Requires-Dist: expert-doc
Requires-Dist: expert-llm
Requires-Dist: tqdm
